suid_core/__init__.py
suid_core/core.py
suid_core/setup.py
suid_core/system.proto
suid_core/system_pb2.py
suid_core/system_pb2.pyi
suid_core/system_pb2_grpc.py
suid_core-1.2.3.dist-info/METADATA
suid_core-1.2.3.dist-info/WHEEL
suid_core-1.2.3.dist-info/entry_points.txt
suid_core-1.2.3.dist-info/RECORD
